setup.py
bgdf_distributions/Binomialdistribution.py
bgdf_distributions/Gaussiandistribution.py
bgdf_distributions/Generaldistribution.py
bgdf_distributions/__init__.py
bgdf_distributions.egg-info/PKG-INFO
bgdf_distributions.egg-info/SOURCES.txt
bgdf_distributions.egg-info/dependency_links.txt
bgdf_distributions.egg-info/not-zip-safe
bgdf_distributions.egg-info/top_level.txt